[{"Driver":"Lewis Hamilton","Nationality":"British","Team":"Mercedes"},{"Driver":"Sebastian Vettel","Nationality":"German","Team":"Aston Martin"},{"Driver":"Fernando Alonso","Nationality":"Spanish","Team":"Alpine"},{"Driver":"Max Verstappen","Nationality":"Dutch","Team":"Red Bull Racing"},{"Driver":"Sergio Perez","Nationality":"Mexican","Team":"Red Bull Racing"},{"Driver":"Charles Leclerc","Nationality":"Monegasque","Team":"Ferrari"},{"Driver":"Daniel Ricciardo","Nationality":"Australian","Team":"McLaren"},{"Driver":"Valtteri Bottas","Nationality":"Finnish","Team":"Alfa Romeo Racing"},{"Driver":"Kimi R\u00e4ikk\u00f6nen","Nationality":"Finnish","Team":"Alfa Romeo Racing"},{"Driver":"Nico H\u00fclkenberg","Nationality":"German","Team":"Aston Martin"},{"Driver":"Carlos Sainz Jr.","Nationality":"Spanish","Team":"Ferrari"},{"Driver":"Lando Norris","Nationality":"British","Team":"McLaren"},{"Driver":"Esteban Ocon","Nationality":"French","Team":"Alpine"},{"Driver":"Pierre Gasly","Nationality":"French","Team":"AlphaTauri"},{"Driver":"Lance Stroll","Nationality":"Canadian","Team":"Aston Martin"},{"Driver":"George Russell","Nationality":"British","Team":"Williams"},{"Driver":"Yuki Tsunoda","Nationality":"Japanese","Team":"AlphaTauri"},{"Driver":"Antonio Giovinazzi","Nationality":"Italian","Team":"Alfa Romeo Racing"},{"Driver":"Nicholas Latifi","Nationality":"Canadian","Team":"Williams"},{"Driver":"Mick Schumacher","Nationality":"German","Team":"Haas"},{"Driver":"Nikita Mazepin","Nationality":"Russian","Team":"Haas"}]